handlers/__init__.py
handlers/tool_handlers.py
models/__init__.py
models/schemas.py
scripts/__init__.py
scripts/get_temp_email.py
services/__init__.py
services/bugbounty_service.py
services/request_service.py
services/webhook_service.py
utils/__init__.py
utils/http_client.py
utils/logger.py
utils/validation.py
py.typed
server.py
webhook_mcp_server-2.1.3.dist-info/METADATA
webhook_mcp_server-2.1.3.dist-info/WHEEL
webhook_mcp_server-2.1.3.dist-info/entry_points.txt
webhook_mcp_server-2.1.3.dist-info/licenses/LICENSE
webhook_mcp_server-2.1.3.dist-info/RECORD
