Metadata-Version: 2.4
Name: webhook-mcp-server
Version: 2.1.3
Summary: MCP Server for webhook.site API integration with layered architecture
Project-URL: Repository, https://github.com/zebbern/webhook-mcp-server
Project-URL: Homepage, https://github.com/zebbern/webhook-mcp-server
Author-email: zebbern <zebbern@users.noreply.github.com>
License: MIT
License-File: LICENSE
Keywords: api-testing,bugbounty,mcp,model-context-protocol,testing,webhook
Classifier: Development Status :: 5 - Production/Stable
Classifier: Intended Audience :: Developers
Classifier: License :: OSI Approved :: MIT License
Classifier: Operating System :: OS Independent
Classifier: Programming Language :: Python :: 3
Classifier: Programming Language :: Python :: 3.10
Classifier: Programming Language :: Python :: 3.11
Classifier: Programming Language :: Python :: 3.12
Classifier: Programming Language :: Python :: 3.13
Classifier: Topic :: Internet :: WWW/HTTP
Classifier: Topic :: Software Development :: Testing
Requires-Python: >=3.10
Requires-Dist: httpx>=0.25.0
Requires-Dist: mcp>=1.0.0
Provides-Extra: dev
Requires-Dist: pytest-asyncio>=1.0.0; extra == 'dev'
Requires-Dist: pytest>=8.0.0; extra == 'dev'
